{"dependencies":[{"name":"/Volumes/Users/kayak/.cix/builds/src/controlr/plugin/client/.babelrc","includedInParent":true,"mtime":1518774302000},{"name":"../assets/iphone-hand.png","loc":{"line":15,"column":21}},{"name":"vue-hot-reload-api","loc":{"line":24,"column":13}}],"generated":{"js":"\"use strict\";Object.defineProperty(exports,\"__esModule\",{value:!0});var e=function(){var e=this.$createElement;this._self._c;return this._m(0)},t=[function(){var e=this.$createElement,t=this._self._c||e;return t(\"div\",[t(\"section\",{staticClass:\"row\"},[t(\"div\",{staticClass:\"col-xs-12 center-xs\"},[t(\"h2\",[this._v(\"ControlR plugin to generate Dockers/VMs user permissions\")])])]),this._v(\" \"),t(\"section\",{staticClass:\"row\"},[t(\"div\",{staticClass:\"col-xs-12 center-xs\"},[t(\"img\",{attrs:{src:require(\"../assets/iphone-hand.png\")}})])])])}];e._withStripped=!0,exports.default={render:e,staticRenderFns:t},module.hot&&(module.hot.accept(),module.hot.data&&require(\"vue-hot-reload-api\").rerender(\"data-v-2e75e705\",module.exports.default));"},"hash":"b185648a7a4c7e37027e413bedf8e015","cacheData":{"env":{}}}